README.rst
setup.py
pyfav/__init__.py
pyfav/pyfav.py
pyfav.egg-info/PKG-INFO
pyfav.egg-info/SOURCES.txt
pyfav.egg-info/dependency_links.txt
pyfav.egg-info/requires.txt
pyfav.egg-info/top_level.txt
test/__init__.py
test/pyfav_test.py