Metadata-Version: 1.1
Name: pyfav
Version: 0.1
Summary: You supply the URL, pyfav will supply the favicon
Home-page: http://github.com/phillipsm/pyfav
Author: Matthew Phillips
Author-email: matt@mattphillips.info
License: http://opensource.org/licenses/MIT
Keywords: favicon,favicons
Platform: UNKNOWN
Classifier: Intended Audience :: Developers
Classifier: Intended Audience :: Science/Research
Classifier: Natural Language :: English
Classifier: License :: OSI Approved :: MIT License
Classifier: Programming Language :: Python
Classifier: Topic :: Internet :: WWW/HTTP
Classifier: Topic :: Internet :: WWW/HTTP :: Site Management :: Link Checking
